MANIFEST.in
README.rst
setup.py
src/unittest_jshint/__init__.py
src/unittest_jshint/case.py
src/unittest_jshint.egg-info/PKG-INFO
src/unittest_jshint.egg-info/SOURCES.txt
src/unittest_jshint.egg-info/dependency_links.txt
src/unittest_jshint.egg-info/entry_points.txt
src/unittest_jshint.egg-info/not-zip-safe
src/unittest_jshint.egg-info/requires.txt
src/unittest_jshint.egg-info/top_level.txt