Metadata-Version: 1.0
Name: unittest-jshint
Version: 1.0
Summary: python unittest integration for jshint
Home-page: https://github.com/garbas/unittest_jshint
Author: Rok Garbas
Author-email: rok@garbas.si
License: BSD
Platform: UNKNOWN
